{
  "updated_at": "2026-04-01T15:38:00+08:00",
  "news": [
    {
      "id": 1,
      "date": "2026-04-01",
      "category": "政策公告",
      "title": "2027年考研时间安排预计发布",
      "summary": "教育部预计将在近期公布2027年全国硕士研究生招生考试时间安排，考生可密切关注教育部官网及研招网通知。",
      "source": "教育部",
      "url": "https://yz.chsi.com.cn/"
    },
    {
      "id": 2,
      "date": "2026-04-01",
      "category": "备考资讯",
      "title": "四月考研复习规划建议",
      "summary": "四月是考研基础阶段的关键期，建议重点夯实英语词汇和长难句基础，数学完成高数第一轮复习，专业课开始通读教材。",
      "source": "考研帮",
      "url": "https://www.kaoyan.com/"
    }
  ]
}
